phmd/__init__.py
phmd/datasets.py
phmd/download.py
phmd/features.py
phmd/utils.py
phmd/metadata/AC16.json
phmd/metadata/AHU21.json
phmd/metadata/ARAMIS20.json
phmd/metadata/BHDD17.json
phmd/metadata/CALCE_CS2.json
phmd/metadata/CALCE_CX2.json
phmd/metadata/CBM14.json
phmd/metadata/CBMv3.json
phmd/metadata/CESNASA15.json
phmd/metadata/CMAPSS.json
phmd/metadata/CNCMILL18.json
phmd/metadata/CWRU.json
phmd/metadata/DFD15.json
phmd/metadata/DUS20.json
phmd/metadata/FCLB19.json
phmd/metadata/GENDEM18.json
phmd/metadata/HIRFNASA15.json
phmd/metadata/HSF15.json
phmd/metadata/HSG18.json
phmd/metadata/IDA16.json
phmd/metadata/IEEE14.json
phmd/metadata/IMS.json
phmd/metadata/JNUB.json
phmd/metadata/KAUG17.json
phmd/metadata/LGB20.json
phmd/metadata/MFPT.json
phmd/metadata/MOSFET11.json
phmd/metadata/MPM20.json
phmd/metadata/NB1.json
phmd/metadata/NB14.json
phmd/metadata/NCMAPSS.json
phmd/metadata/NMILL.json
phmd/metadata/OBDD17.json
phmd/metadata/PBCP16.json
phmd/metadata/PBHP16.json
phmd/metadata/PHM10.json
phmd/metadata/PHM13.json
phmd/metadata/PHM14.json
phmd/metadata/PHM15.json
phmd/metadata/PHM16.json
phmd/metadata/PHM18.json
phmd/metadata/PHM19.json
phmd/metadata/PHMAP21.json
phmd/metadata/PHMAP23.json
phmd/metadata/PHME20.json
phmd/metadata/PHME24.json
phmd/metadata/PPD18.json
phmd/metadata/PRONOSTIA.json
phmd/metadata/PTRB19.json
phmd/metadata/PUBD16.json
phmd/metadata/RRB23.json
phmd/metadata/SEUGB17.json
phmd/metadata/SSPSNASA15.json
phmd/metadata/STEELPLATES.json
phmd/metadata/UNIBO21.json
phmd/metadata/UOC18.json
phmd/metadata/UPM20.json
phmd/metadata/UPM23.json
phmd/metadata/XJTU-SY.json
phmd/metadata/__init__.py
phmd/readers/__init__.py
phmd/readers/ac16.py
phmd/readers/ahu21.py
phmd/readers/aramis20.py
phmd/readers/base.py
phmd/readers/bhdd17.py
phmd/readers/calce_cs2.py
phmd/readers/calce_cx2.py
phmd/readers/cbm14.py
phmd/readers/cbmv3.py
phmd/readers/cesnasa15.py
phmd/readers/cmapss.py
phmd/readers/cncmill18.py
phmd/readers/curves.py
phmd/readers/cwru.py
phmd-20204.0.1.dist-info/LICENSE
phmd-20204.0.1.dist-info/METADATA
phmd-20204.0.1.dist-info/WHEEL
phmd-20204.0.1.dist-info/top_level.txt
phmd-20204.0.1.dist-info/RECORD
