Metadata-Version: 2.1
Name: phmd
Version: 20204.0.1
Summary: The library `phmd` is designed to facilitate access to datasets in the context of industrial prognosis and health management (PHM)
Home-page: https://github.com/dasolma/phmd
Author: David Solís-Martín
Author-email: dsolis@us.es
Maintainer: David Solís-Martín
Maintainer-email: dsolis@us.es
License: Apache
Keywords: predictive maintenance,condition monitoring,datasets,gear,bearing,battery,AI,artificial intelligence
Classifier: Programming Language :: Python :: 3
Classifier: License :: OSI Approved :: Apache Software License
Classifier: Operating System :: OS Independent
License-File: LICENSE
Requires-Dist: gdown ==5.2.0
Requires-Dist: pandas ==2.0.3
Requires-Dist: h5py ==3.11.0
Requires-Dist: scipy ==1.10.1
Requires-Dist: openpyxl ==3.1.5
Requires-Dist: tabulate ==0.9.0
Requires-Dist: PyWavelets ==1.4.1
Requires-Dist: scikit-learn ==1.3.2
